krakenings_discord_bot/__init__.py
krakenings_discord_bot/__main__.py
krakenings_discord_bot/bot.py
krakenings_discord_bot/cli.py
krakenings_discord_bot/espn.py
krakenings_discord_bot/event.py
krakenings_discord_bot/images.py
krakenings_discord_bot-0.1.2.dist-info/METADATA
krakenings_discord_bot-0.1.2.dist-info/WHEEL
krakenings_discord_bot-0.1.2.dist-info/entry_points.txt
krakenings_discord_bot-0.1.2.dist-info/RECORD
