Metadata-Version: 2.4
Name: krakenings-discord-bot
Version: 0.1.2
Summary: discord bot for Krakenings schedule
License: MIT
Requires-Python: ~=3.13.0
Requires-Dist: aiohttp~=3.11.11
Requires-Dist: audioop-lts; python_version >= '3.13'
Requires-Dist: click>=8.1.8
Requires-Dist: discord-py~=2.4.0
Requires-Dist: environ-config>=24.1.0
Requires-Dist: httpx>=0.28.1
Requires-Dist: humanize>=4.11.0
Requires-Dist: icecream>=2.1.4
Requires-Dist: nhl-stats-client>=1.0.0
Requires-Dist: numpy>=2.2.2
Requires-Dist: pillow>=11.1.0
Requires-Dist: pydantic-extra-types>=2.10.2
Requires-Dist: pydantic>=2.10.6
Requires-Dist: python-dateutil~=2.8.2
Requires-Dist: rich>=13.9.4
Requires-Dist: svcs>=25.1.0
Requires-Dist: tomli>=2.2.1
